rsarmageddon/__init__.py
rsarmageddon/__main__.py
rsarmageddon/args.py
rsarmageddon/attacks.py
rsarmageddon/banner.py
rsarmageddon/certs.py
rsarmageddon/crypto.py
rsarmageddon/parsing.py
rsarmageddon/sage.py
rsarmageddon/attack_lib/__init__.py
rsarmageddon/attack_lib/attack.py
rsarmageddon/builtin_attacks/00_factordb.sage
rsarmageddon/builtin_attacks/05_wiener.sage
rsarmageddon/builtin_attacks/10_fermat.sage
rsarmageddon/builtin_attacks/15_mersenne.sage
rsarmageddon/builtin_attacks/20_novelty.sage
rsarmageddon/builtin_attacks/25_small_factor.sage
rsarmageddon/builtin_attacks/30_small_fraction.sage
rsarmageddon/builtin_attacks/35_common_modulus.sage
rsarmageddon/builtin_attacks/40_hastad.sage
rsarmageddon/builtin_attacks/45_common_factor.sage
rsarmageddon/builtin_attacks/50_p-1.sage
rsarmageddon/builtin_attacks/55_qicheng.sage
rsarmageddon/builtin_attacks/85_londahl.sage
rsarmageddon/builtin_attacks/90_boneh_durfee.sage
rsarmageddon/builtin_attacks/__init__.py
rsarmageddon/commands/__init__.py
rsarmageddon/commands/attack.py
rsarmageddon/commands/ciphertool.py
rsarmageddon/commands/misc.py
rsarmageddon/commands/pem.py
rsarmageddon/scripts/__init__.py
rsarmageddon/scripts/ecm_factor.sage
rsarmageddon/scripts/euler_phi.sage
rsarmageddon/scripts/factor.sage
rsarmageddon/scripts/isprime.sage
rsarmageddon/utils/__init__.py
rsarmageddon/utils/output.py
rsarmageddon-2.1.1.dist-info/LICENSE
rsarmageddon-2.1.1.dist-info/METADATA
rsarmageddon-2.1.1.dist-info/WHEEL
rsarmageddon-2.1.1.dist-info/entry_points.txt
rsarmageddon-2.1.1.dist-info/top_level.txt
rsarmageddon-2.1.1.dist-info/RECORD
