Metadata-Version: 2.1
Name: rsarmageddon
Version: 2.1.1
Summary: RSA cryptography and cryptoanalysis toolkit
Home-page: https://github.com/m1gnus/RSArmageddon
Author: Vittorio Mignini <vittorio.mignini@gmail.com>, Simone Cimarelli <aquilairreale@ymail.com>
Author-email: vittorio.mignini@gmail.com
License: UNKNOWN
Project-URL: Bug Tracker, https://github.com/m1gnus/RSArmageddon/issues
Platform: UNKNOWN
Classifier: Development Status :: 5 - Production/Stable
Classifier: Environment :: Console
Classifier: Intended Audience :: Science/Research
Classifier: License :: OSI Approved :: GNU General Public License v3 (GPLv3)
Classifier: Programming Language :: Python :: 3
Classifier: Operating System :: POSIX :: Linux
Classifier: Operating System :: MacOS :: MacOS X
Classifier: Operating System :: Microsoft :: Windows
Classifier: Topic :: Security :: Cryptography
Requires-Python: >=3.7
License-File: LICENSE
Requires-Dist: colorama
Requires-Dist: pycryptodome
Requires-Dist: gmpy2
Requires-Dist: psutil
